pyvlasiator/__init__.py
pyvlasiator/pyvlasiator.py
pyvlasiator/plot/__init__.py
pyvlasiator/plot/plot.py
pyvlasiator/vlsv/__init__.py
pyvlasiator/vlsv/reader.py
pyvlasiator/vlsv/variables.py
pyvlasiator-0.1.10.dist-info/licenses/LICENSE.md
pyvlasiator-0.1.10.dist-info/METADATA
pyvlasiator-0.1.10.dist-info/WHEEL
pyvlasiator-0.1.10.dist-info/top_level.txt
pyvlasiator-0.1.10.dist-info/RECORD
