Metadata-Version: 2.4
Name: pyvlasiator
Version: 0.1.10
Summary: Python utilities for processing Vlasiator data
Author-email: Hongyang Zhou <hyzhou@umich.edu>
Requires-Python: <4.0,>=3.11
License-File: LICENSE.md
Requires-Dist: numpy>=1.25.1
Provides-Extra: plot
Requires-Dist: matplotlib<4,>=3.7.2; extra == "plot"
Provides-Extra: dev
Requires-Dist: pytest<8,>=7.4.0; extra == "dev"
Requires-Dist: pytest-benchmark<5,>=4.0.0; extra == "dev"
Requires-Dist: pytest-cov<5,>=4.1.0; extra == "dev"
Requires-Dist: requests<3,>=2.31.0; extra == "dev"
Requires-Dist: jupyter<2,>=1.0.0; extra == "dev"
Requires-Dist: myst-nb<2,>=1.0.0; extra == "dev"
Requires-Dist: sphinx-autoapi<4,>=3.0.0; extra == "dev"
Requires-Dist: sphinx-rtd-theme<2,>=1.2.2; extra == "dev"
Dynamic: license-file
